{"ads_id": 1, "lat": 24.7451076, "price": 1161.0, "description": "", "address": "Espoo, Matinkyla, Matinniitynkuja 1"}{"ads_id": 2, "lat": 24.8672907, "price": 1370.0, "description": "", "address": "Helsinki, Malminkartano, Luutnantinpolku 7 E 64"}{"ads_id": 3, "lat": 24.7451076, "price": 1161.0, "description": "", "address": "Espoo, Matinkyla, Matinniitynkuja 1"}{"ads_id": 4, "lat": 24.8672907, "price": 1370.0, "description": "", "address": "Helsinki, Malminkartano, Luutnantinpolku 7 E 64"}{"ads_id": 5, "lat": 24.7451076, "price": 1161.0, "description": "", "address": "Espoo, Matinkyla, Matinniitynkuja 1"}{"ads_id": 6, "lat": 24.8672907, "price": 1370.0, "description": "", "address": "Helsinki, Malminkartano, Luutnantinpolku 7 E 64"}